oddswrangler/__init__.py
oddswrangler-0.0.0.dist-info/METADATA
oddswrangler-0.0.0.dist-info/WHEEL
oddswrangler-0.0.0.dist-info/top_level.txt
oddswrangler-0.0.0.dist-info/RECORD
