Metadata-Version: 2.1
Name: oddswrangler
Version: 0.0.0
Summary: Coming soon
Author-email: Dejon Wright <dejon.wright@gmail.com>
